dsge/DSGE.py
dsge/FCodePrinter.py
dsge/OtherPriors.py
dsge/Prior.py
dsge/StateSpaceModel.py
dsge/__init__.py
dsge/data.py
dsge/examples.py
dsge/filters.py
dsge/gensys.py
dsge/helper_functions.py
dsge/symbols.py
dsge/translate.py
dsge/examples/DGS/DGSfunc.py
dsge/examples/ar1/ar1.yaml
dsge/examples/ar1/arma23_sim200.txt
dsge/examples/ar1/sim100.txt
dsge/examples/edo/edo.yaml
dsge/examples/edo/siedo.yaml
dsge/examples/nkmp/dsge1.yaml
dsge/examples/nkmp/nkmp.yaml
dsge/examples/nkmp/nkmp_base.yaml
dsge/examples/nkmp/nkmp_base_with_lev.yaml
dsge/examples/nkmp/nkmp_diffuse.yaml
dsge/examples/nkmp/nkmp_diffuse_with_lev.yaml
dsge/examples/nkmp/nkmp_exp_test.yaml
dsge/examples/nkmp/nkmp_lev.yaml
dsge/examples/nkmp/test_lags.yaml
dsge/examples/nkmp/us.txt
dsge/examples/schorf_phillips_curve/schorf_phillips_curve.yaml
dsge/examples/simple-model/simple_model.yaml
dsge/examples/simple-model/simple_model_est.yaml
dsge/examples/sw/YY.txt
dsge/examples/sw/sw.yaml
dsge/misc/__init__.py
dsge/misc/yaml_adjustment.py
dsge/tests/__init__.py
dsge/tests/test_abcd.py
dsge/tests/test_equations.py
dsge/tests/test_export.py
dsge/tests/test_filter.py
dsge/tests/test_gensys.py
dsge/tests/test_other_para.py
dsge/tests/test_pickle.py
dsge-0.1.3.dist-info/METADATA
dsge-0.1.3.dist-info/WHEEL
dsge-0.1.3.dist-info/top_level.txt
dsge-0.1.3.dist-info/RECORD
